setup.py
format257/__init__.py
format257.egg-info/PKG-INFO
format257.egg-info/SOURCES.txt
format257.egg-info/dependency_links.txt
format257.egg-info/top_level.txt