Metadata-Version: 1.1
Name: format257
Version: 1.0.0
Summary: Format docstrings as per PEP 257
Home-page: https://github.com/brennie/format257
Author: Barret Rennie
Author-email: barret@brennie.ca
License: Public Domain
Platform: UNKNOWN
Classifier: Development Status :: 7 - Inactive
Classifier: License :: Public Domain
Classifier: Programming Language :: Python :: 2
Classifier: Programming Language :: Python :: 3
